llmtaskkit/__init__.py
llmtaskkit/core/__init__.py
llmtaskkit/core/llm/__init__.py
llmtaskkit/core/llm/llm_config.py
llmtaskkit/core/prompt/__init__.py
llmtaskkit/core/prompt/markdown_prompt_builder.py
llmtaskkit/core/prompt/prompt_builder.py
llmtaskkit/core/prompt/tests/__init__.py
llmtaskkit/core/prompt/tests/test_xml_prompt_builder.py
llmtaskkit/core/prompt/xml_prompt_builder.py
llmtaskkit/core/task/__init__.py
llmtaskkit/core/task/raw_task.py
llmtaskkit/core/task/task.py
llmtaskkit/core/task/task_executor.py
llmtaskkit/core/task/task_loader.py
llmtaskkit/core/task/tests/__init__.py
llmtaskkit/core/task/tests/test_task.py
llmtaskkit/core/task/tests/test_task_executor.py
llmtaskkit/example/meeting_summary/__init__.py
llmtaskkit/example/meeting_summary/__main__.py
llmtaskkit/example/meeting_summary/meeting_summary.py
llmtaskkit/example/meeting_summary/meeting_summary_tasks_en.yaml
llmtaskkit/example/meeting_summary/meeting_summary_tasks_fr.yaml
llmtaskkit/example/meeting_summary/readme.md
llmtaskkit/example/prompt_finetuner/__init__.py
llmtaskkit/example/prompt_finetuner/__main__.py
llmtaskkit/example/prompt_finetuner/prompt_finetuner.py
llmtaskkit/example/prompt_finetuner/prompts_finetuner_tasks_en.yaml
llmtaskkit/example/prompt_finetuner/prompts_finetuner_tasks_fr.yaml
llmtaskkit/example/prompt_finetuner/readme.md
llmtaskkit/prompt_chain/__init__.py
llmtaskkit/prompt_chain/task_chain_executor.py
llmtaskkit-1.1.1.dist-info/LICENSE
llmtaskkit-1.1.1.dist-info/METADATA
llmtaskkit-1.1.1.dist-info/WHEEL
llmtaskkit-1.1.1.dist-info/RECORD
