Metadata-Version: 2.3
Name: llmtaskkit
Version: 1.1.1
Summary: A Python bookstore to simplify the definition, execution and chaining of tasks using LLMS.
License: GNU General Public License v3 (GPLv3)
Author: Herzog Robin
Requires-Python: >=3.8,<4.0
Classifier: Development Status :: 4 - Beta
Classifier: Intended Audience :: Developers
Classifier: Programming Language :: Python :: 3
Classifier: License :: OSI Approved :: GNU General Public License v3 (GPLv3)
Classifier: Operating System :: OS Independent
Requires-Dist: litellm (>=1.62.1,<1.63.0)
Requires-Dist: pydantic (>=2.10.6,<3.0.0)
Requires-Dist: python-dotenv (>=1.0.1,<2.0.0)
Requires-Dist: pyyaml (>=6.0.2,<7.0.0)
Project-URL: Homepage, https://github.com/gartu/LLMTaskKit
